backoff/__init__.py
backoff/_async.py
backoff/_common.py
backoff/_decorator.py
backoff/_jitter.py
backoff/_sync.py
backoff/_typing.py
backoff/_wait_gen.py
backoff/py.typed
backoff/types.py
python_backoff-2.3.1.dist-info/METADATA
python_backoff-2.3.1.dist-info/WHEEL
python_backoff-2.3.1.dist-info/licenses/LICENSE
python_backoff-2.3.1.dist-info/RECORD
