Metadata-Version: 2.4
Name: python-backoff
Version: 2.3.1
Summary: Function decoration for backoff and retry
Project-URL: Documentation, https://python-backoff.github.io/backoff
Project-URL: Repository, https://github.com/python-backoff/backoff
Author-email: Bob Green <rgreen@aquent.com>
Maintainer-email: Edgar Ramírez-Mondragón <edgarrm358@gmail.com>
License-Expression: MIT
License-File: LICENSE
Keywords: backoff,decorators,retry
Classifier: Development Status :: 5 - Production/Stable
Classifier: Intended Audience :: Developers
Classifier: License :: OSI Approved :: MIT License
Classifier: Natural Language :: English
Classifier: Operating System :: OS Independent
Classifier: Programming Language :: Python
Classifier: Programming Language :: Python :: 3
Classifier: Programming Language :: Python :: 3.8
Classifier: Programming Language :: Python :: 3.9
Classifier: Programming Language :: Python :: 3.10
Classifier: Programming Language :: Python :: 3.11
Classifier: Programming Language :: Python :: 3.12
Classifier: Programming Language :: Python :: 3.13
Classifier: Programming Language :: Python :: 3.14
Classifier: Programming Language :: Python :: 3.15
Classifier: Topic :: Internet :: WWW/HTTP
Classifier: Topic :: Software Development :: Libraries :: Python Modules
Classifier: Topic :: Utilities
Requires-Python: >=3.8
